dfs/__init__.py
dfs/command.py
dfs/main.py
dfs/models.py
dfs/state.py
dfs/version.py
dfs/load/__init__.py
dfs/load/load.py
dfs/load/scrape.py
dfs/optimize/__init__.py
dfs/optimize/generate_lineup.py
dfs/optimize/generate_lineup_test.py
dfs/optimize/optimize.py
dfs/projections/__init__.py
dfs_lineup_optimizer-0.0.12.dist-info/METADATA
dfs_lineup_optimizer-0.0.12.dist-info/WHEEL
dfs_lineup_optimizer-0.0.12.dist-info/entry_points.txt
dfs_lineup_optimizer-0.0.12.dist-info/top_level.txt
dfs_lineup_optimizer-0.0.12.dist-info/RECORD
