Metadata-Version: 2.1
Name: dfs-lineup-optimizer
Version: 0.0.12
Summary: Generate optimal DFS lineups
Home-page: https://github.com/amamparo/dfs-lineup-optimizer
Author: Aaron Mamparo
Author-email: aaronmamparo@gmail.com
License: UNKNOWN
Platform: UNKNOWN
Classifier: Programming Language :: Python :: 3
Classifier: License :: OSI Approved :: MIT License
Classifier: Operating System :: OS Independent
Requires-Python: >= 3.8
Requires-Dist: argparse (==1.4.0)
Requires-Dist: certifi (==2020.6.20)
Requires-Dist: chardet (==3.0.4)
Requires-Dist: pulp (==2.3.1)
Requires-Dist: requests (==2.24.0)
Requires-Dist: pyparsing (==2.4.7) ; python_version >= "2.6" and python_version not in "3.0, 3.1, 3.2, 3.3"
Requires-Dist: amply (==0.1.4) ; python_version >= "2.7" and python_version not in "3.0, 3.1, 3.2, 3.3"
Requires-Dist: idna (==2.10) ; python_version >= "2.7" and python_version not in "3.0, 3.1, 3.2, 3.3"
Requires-Dist: docutils (==0.16) ; python_version >= "2.7" and python_version not in "3.0, 3.1, 3.2, 3.3, 3.4"
Requires-Dist: urllib3 (==1.25.11) ; python_version >= "2.7" and python_version not in "3.0, 3.1, 3.2, 3.3, 3.4" and python_version < "4"
